netbox_interface_sync/__init__.py
netbox_interface_sync/forms.py
netbox_interface_sync/template_content.py
netbox_interface_sync/urls.py
netbox_interface_sync/utils.py
netbox_interface_sync/views.py
netbox_interface_sync/templates/netbox_interface_sync/compare_interfaces_button.html
netbox_interface_sync/templates/netbox_interface_sync/interface_comparison.html
netbox_interface_sync/templates/netbox_interface_sync/number_of_interfaces_panel.html
netbox_interface_sync-0.1.3.dist-info/METADATA
netbox_interface_sync-0.1.3.dist-info/WHEEL
netbox_interface_sync-0.1.3.dist-info/top_level.txt
netbox_interface_sync-0.1.3.dist-info/RECORD
